pacotebmi/__init__.py
pacotebmi/arquivobmi.py
pacotebmi-0.0.3.dist-info/LICENSE.txt
pacotebmi-0.0.3.dist-info/METADATA
pacotebmi-0.0.3.dist-info/WHEEL
pacotebmi-0.0.3.dist-info/top_level.txt
pacotebmi-0.0.3.dist-info/RECORD
